civicstream/__init__.py
civicstream/civicstream.py
civicstream-1.0.3.dist-info/licenses/LICENSE
civicstream-1.0.3.dist-info/METADATA
civicstream-1.0.3.dist-info/WHEEL
civicstream-1.0.3.dist-info/entry_points.txt
civicstream-1.0.3.dist-info/top_level.txt
civicstream-1.0.3.dist-info/RECORD
